pylucam/__init__.py
pylucam/api.py
pylucam/camera.py
pylucam/include/lucamapi.h
pylucam-1.0.3.dist-info/licenses/LICENSE
pylucam-1.0.3.dist-info/METADATA
pylucam-1.0.3.dist-info/WHEEL
pylucam-1.0.3.dist-info/top_level.txt
pylucam-1.0.3.dist-info/RECORD
