Metadata-Version: 2.4
Name: pylucam
Version: 1.0.3
Summary: Python wrapper for Lumenera Lucam API
Author-email: Jacob Gobbo <gobbo.jacob@gmail.com>
License-Expression: GPL-3.0-only
Project-URL: Repository, https://github.com/jgobbo/pylucam
Keywords: python,lucam,lumenera,camera,api,driver
Requires-Python: >=3.11
License-File: LICENSE
Requires-Dist: cffi>=1.17.1
Requires-Dist: numpy>=2.2.5
Requires-Dist: opencv-python>=4.11.0.86
Dynamic: license-file
